filecomptroller/__init__.py
filecomptroller/split.py
filecomptroller-0.0.1.dist-info/LICENSE
filecomptroller-0.0.1.dist-info/METADATA
filecomptroller-0.0.1.dist-info/WHEEL
filecomptroller-0.0.1.dist-info/top_level.txt
filecomptroller-0.0.1.dist-info/RECORD
