Metadata-Version: 2.1
Name: filecomptroller
Version: 0.0.1
Summary: Manage and modify your files
Author: DevStrikerTech (Nishat)
Author-email: 
Keywords: split file,marge file,zip file,unzip file
Classifier: Development Status :: 1 - Planning
Classifier: Intended Audience :: Developers
Classifier: Programming Language :: Python :: 3
Classifier: Operating System :: Unix
Classifier: Operating System :: MacOS :: MacOS X
Classifier: Operating System :: Microsoft :: Windows
License-File: LICENSE
